{"kind":"article","schemaVersion":{"minor":3,"patch":0,"major":0},"variants":[{"paths":["\/documentation\/cloudxrkit\/sessionapi"],"traits":[{"interfaceLanguage":"swift"}]},{"paths":["\/documentation\/cloudxrkit\/sessionapi"],"traits":[{"interfaceLanguage":"occ"}]}],"sections":[],"primaryContentSections":[{"kind":"content","content":[{"anchor":"Overview","type":"heading","level":2,"text":"Overview"},{"type":"paragraph","inlineContent":[{"text":"Clients use ","type":"text"},{"isActive":true,"type":"reference","identifier":"doc:\/\/com.nvidia.CloudXRKit\/documentation\/CloudXRKit\/CloudXRSession"},{"text":" to configure, initiate, pause, resume, and end a streaming session. In addition, ","type":"text"},{"isActive":true,"type":"reference","identifier":"doc:\/\/com.nvidia.CloudXRKit\/documentation\/CloudXRKit\/CloudXRSession"},{"text":" maintains the current session state for the client.","type":"text"}]},{"anchor":"Session-life-cycle","type":"heading","level":3,"text":"Session life cycle"},{"type":"paragraph","inlineContent":[{"identifier":"SessionAPIDiagram.png","type":"image"}]},{"anchor":"Operations","type":"heading","level":3,"text":"Operations"},{"type":"paragraph","inlineContent":[{"text":"As the above diagram illustrates, there are a few operations clients can perform to manage a streaming session:","type":"text"}]},{"anchor":"Configuration","type":"heading","level":4,"text":"Configuration"},{"type":"paragraph","inlineContent":[{"type":"text","text":"The session needs to be configured before it can begin. The client defines the configuration as a "},{"identifier":"doc:\/\/com.nvidia.CloudXRKit\/documentation\/CloudXRKit\/Config","type":"reference","isActive":true},{"type":"text","text":" and uses that to initialize a "},{"identifier":"doc:\/\/com.nvidia.CloudXRKit\/documentation\/CloudXRKit\/CloudXRSession","type":"reference","isActive":true},{"type":"text","text":" instance. Optionally, the configuration can be updated for an existing "},{"identifier":"doc:\/\/com.nvidia.CloudXRKit\/documentation\/CloudXRKit\/CloudXRSession","type":"reference","isActive":true},{"type":"text","text":" with "},{"identifier":"doc:\/\/com.nvidia.CloudXRKit\/documentation\/CloudXRKit\/CloudXRSession\/configure(config:)","type":"reference","isActive":true},{"type":"text","text":". Any prior sessions must be disconnected before calling "},{"identifier":"doc:\/\/com.nvidia.CloudXRKit\/documentation\/CloudXRKit\/CloudXRSession\/configure(config:)","type":"reference","isActive":true},{"type":"text","text":"."}]},{"type":"paragraph","inlineContent":[{"text":"The ","type":"text"},{"isActive":true,"identifier":"doc:\/\/com.nvidia.CloudXRKit\/documentation\/CloudXRKit\/Config","type":"reference"},{"text":" field ","type":"text"},{"isActive":true,"identifier":"doc:\/\/com.nvidia.CloudXRKit\/documentation\/CloudXRKit\/Config\/resolutionPreset","type":"reference"},{"text":" can only changed for a ","type":"text"},{"isActive":true,"identifier":"doc:\/\/com.nvidia.CloudXRKit\/documentation\/CloudXRKit\/CloudXRSession","type":"reference"},{"text":" instance that is still in the ","type":"text"},{"isActive":true,"identifier":"doc:\/\/com.nvidia.CloudXRKit\/documentation\/CloudXRKit\/SessionState\/initialized","type":"reference"},{"text":" state; once a connection has been initiated, any updates to ","type":"text"},{"isActive":true,"identifier":"doc:\/\/com.nvidia.CloudXRKit\/documentation\/CloudXRKit\/Config\/resolutionPreset","type":"reference"},{"text":" in subsequent calls to ","type":"text"},{"isActive":true,"identifier":"doc:\/\/com.nvidia.CloudXRKit\/documentation\/CloudXRKit\/CloudXRSession\/configure(config:)","type":"reference"},{"text":" will be ignored.","type":"text"}]},{"anchor":"Connection","type":"heading","level":4,"text":"Connection"},{"type":"paragraph","inlineContent":[{"type":"text","text":"The client calls "},{"isActive":true,"identifier":"doc:\/\/com.nvidia.CloudXRKit\/documentation\/CloudXRKit\/CloudXRSession\/connect()","type":"reference"},{"type":"text","text":" to start the session. This first performs any authentication steps that may be needed if using GDN, and then initiates the connection. It is asynchronous and returns when the session reaches the "},{"isActive":true,"identifier":"doc:\/\/com.nvidia.CloudXRKit\/documentation\/CloudXRKit\/SessionState\/connecting","type":"reference"},{"type":"text","text":" state."}]},{"anchor":"Disconnection","type":"heading","level":4,"text":"Disconnection"},{"type":"paragraph","inlineContent":[{"isActive":true,"type":"reference","identifier":"doc:\/\/com.nvidia.CloudXRKit\/documentation\/CloudXRKit\/CloudXRSession\/disconnect()"},{"type":"text","text":" disconnects the client and deletes a session."}]},{"anchor":"Pausing-and-resuming","type":"heading","level":4,"text":"Pausing and resuming"},{"type":"paragraph","inlineContent":[{"identifier":"doc:\/\/com.nvidia.CloudXRKit\/documentation\/CloudXRKit\/CloudXRSession\/pause()","type":"reference","isActive":true},{"type":"text","text":" disconnects a session without deleting it (e.g. to keep using the same GDN host when resuming). Note that GDN will time out after 180 seconds of being paused if the client does not reconnect."}]},{"type":"paragraph","inlineContent":[{"type":"text","text":"To reconnect to a paused session, call "},{"type":"reference","identifier":"doc:\/\/com.nvidia.CloudXRKit\/documentation\/CloudXRKit\/CloudXRSession\/resume()","isActive":true},{"type":"text","text":"."}]},{"anchor":"State","type":"heading","level":3,"text":"State"},{"type":"paragraph","inlineContent":[{"text":"Clients can get the current ","type":"text"},{"identifier":"doc:\/\/com.nvidia.CloudXRKit\/documentation\/CloudXRKit\/SessionState","isActive":true,"type":"reference"},{"text":" from ","type":"text"},{"identifier":"doc:\/\/com.nvidia.CloudXRKit\/documentation\/CloudXRKit\/Session\/state","isActive":true,"type":"reference"},{"text":".","type":"text"}]}]}],"abstract":[{"text":"API to manage the life cycle of a session with the server.","type":"text"}],"metadata":{"title":"Session API","modules":[{"name":"CloudXRKit"}],"roleHeading":"Article","role":"article"},"hierarchy":{"paths":[["doc:\/\/com.nvidia.CloudXRKit\/documentation\/CloudXRKit"]]},"identifier":{"interfaceLanguage":"swift","url":"doc:\/\/com.nvidia.CloudXRKit\/documentation\/CloudXRKit\/SessionAPI"},"references":{"doc://com.nvidia.CloudXRKit/documentation/CloudXRKit/Config/resolutionPreset":{"identifier":"doc:\/\/com.nvidia.CloudXRKit\/documentation\/CloudXRKit\/Config\/resolutionPreset","title":"resolutionPreset","fragments":[{"text":"var","kind":"keyword"},{"text":" ","kind":"text"},{"text":"resolutionPreset","kind":"identifier"},{"text":": ","kind":"text"},{"text":"ResolutionPreset","kind":"typeIdentifier","preciseIdentifier":"s:10CloudXRKit16ResolutionPresetO"}],"abstract":[{"type":"text","text":"The resolution preset cannot be changed after the first connection."}],"type":"topic","url":"\/documentation\/cloudxrkit\/config\/resolutionpreset","kind":"symbol","role":"symbol"},"doc://com.nvidia.CloudXRKit/documentation/CloudXRKit/CloudXRSession/init(config:)":{"role":"symbol","title":"init(config:)","type":"topic","identifier":"doc:\/\/com.nvidia.CloudXRKit\/documentation\/CloudXRKit\/CloudXRSession\/init(config:)","kind":"symbol","fragments":[{"text":"init","kind":"identifier"},{"text":"(","kind":"text"},{"text":"config","kind":"externalParam"},{"text":": ","kind":"text"},{"text":"Config","kind":"typeIdentifier","preciseIdentifier":"s:10CloudXRKit6ConfigV"},{"text":")","kind":"text"}],"abstract":[{"text":"The constructor takes the initial ","type":"text"},{"isActive":true,"identifier":"doc:\/\/com.nvidia.CloudXRKit\/documentation\/CloudXRKit\/Config","type":"reference"},{"text":" for the session.","type":"text"},{"text":" ","type":"text"},{"text":"The config can optionally be updated later with ","type":"text"},{"isActive":true,"identifier":"doc:\/\/com.nvidia.CloudXRKit\/documentation\/CloudXRKit\/CloudXRSession\/configure(config:)","type":"reference"},{"text":".","type":"text"}],"url":"\/documentation\/cloudxrkit\/cloudxrsession\/init(config:)"},"doc://com.nvidia.CloudXRKit/documentation/CloudXRKit/SessionState/connecting":{"type":"topic","title":"SessionState.connecting","url":"\/documentation\/cloudxrkit\/sessionstate\/connecting","fragments":[{"text":"case","kind":"keyword"},{"text":" ","kind":"text"},{"text":"connecting","kind":"identifier"}],"abstract":[],"identifier":"doc:\/\/com.nvidia.CloudXRKit\/documentation\/CloudXRKit\/SessionState\/connecting","role":"symbol","kind":"symbol"},"doc://com.nvidia.CloudXRKit/documentation/CloudXRKit/CloudXRSession":{"role":"symbol","abstract":[{"type":"text","text":"Manages a CloudXR session."}],"identifier":"doc:\/\/com.nvidia.CloudXRKit\/documentation\/CloudXRKit\/CloudXRSession","type":"topic","kind":"symbol","fragments":[{"text":"class","kind":"keyword"},{"text":" ","kind":"text"},{"text":"CloudXRSession","kind":"identifier"}],"navigatorTitle":[{"text":"CloudXRSession","kind":"identifier"}],"title":"CloudXRSession","url":"\/documentation\/cloudxrkit\/cloudxrsession"},"doc://com.nvidia.CloudXRKit/documentation/CloudXRKit":{"title":"CloudXRKit","identifier":"doc:\/\/com.nvidia.CloudXRKit\/documentation\/CloudXRKit","type":"topic","role":"collection","kind":"symbol","abstract":[{"text":"Stream immersive applications.","type":"text"}],"url":"\/documentation\/cloudxrkit"},"doc://com.nvidia.CloudXRKit/documentation/CloudXRKit/CloudXRSession/connect()":{"type":"topic","abstract":[{"type":"text","text":"Initiates server connection and authentication based on client configuration from "},{"type":"reference","identifier":"doc:\/\/com.nvidia.CloudXRKit\/documentation\/CloudXRKit\/CloudXRSession\/init(config:)","isActive":true},{"type":"text","text":" or "},{"type":"reference","identifier":"doc:\/\/com.nvidia.CloudXRKit\/documentation\/CloudXRKit\/CloudXRSession\/configure(config:)","isActive":true},{"type":"text","text":"."},{"type":"text","text":" "},{"type":"text","text":"It returns once any authentication is finished and the connection setup has been initiated, but potentially before the actual connection is"},{"type":"text","text":" "},{"type":"text","text":"established."}],"identifier":"doc:\/\/com.nvidia.CloudXRKit\/documentation\/CloudXRKit\/CloudXRSession\/connect()","title":"connect()","role":"symbol","url":"\/documentation\/cloudxrkit\/cloudxrsession\/connect()","kind":"symbol","fragments":[{"kind":"keyword","text":"func"},{"kind":"text","text":" "},{"kind":"identifier","text":"connect"},{"kind":"text","text":"() "},{"kind":"keyword","text":"async"},{"kind":"text","text":" "},{"kind":"keyword","text":"throws"}]},"doc://com.nvidia.CloudXRKit/documentation/CloudXRKit/SessionState/initialized":{"role":"symbol","abstract":[],"kind":"symbol","type":"topic","title":"SessionState.initialized","url":"\/documentation\/cloudxrkit\/sessionstate\/initialized","identifier":"doc:\/\/com.nvidia.CloudXRKit\/documentation\/CloudXRKit\/SessionState\/initialized","fragments":[{"text":"case","kind":"keyword"},{"text":" ","kind":"text"},{"text":"initialized","kind":"identifier"}]},"doc://com.nvidia.CloudXRKit/documentation/CloudXRKit/Config":{"kind":"symbol","role":"symbol","identifier":"doc:\/\/com.nvidia.CloudXRKit\/documentation\/CloudXRKit\/Config","fragments":[{"text":"struct","kind":"keyword"},{"text":" ","kind":"text"},{"text":"Config","kind":"identifier"}],"url":"\/documentation\/cloudxrkit\/config","abstract":[{"text":"Specifies how to configure a Session.","type":"text"}],"type":"topic","title":"Config","navigatorTitle":[{"text":"Config","kind":"identifier"}]},"doc://com.nvidia.CloudXRKit/documentation/CloudXRKit/CloudXRSession/configure(config:)":{"abstract":[{"text":"Updates session configuration. This is implicitly called by ","type":"text"},{"isActive":true,"identifier":"doc:\/\/com.nvidia.CloudXRKit\/documentation\/CloudXRKit\/CloudXRSession\/init(config:)","type":"reference"},{"text":" already, so the client would only use it to reconfigure an","type":"text"},{"text":" ","type":"text"},{"text":"existing ","type":"text"},{"isActive":true,"identifier":"doc:\/\/com.nvidia.CloudXRKit\/documentation\/CloudXRKit\/CloudXRSession","type":"reference"},{"text":" instance.","type":"text"}],"url":"\/documentation\/cloudxrkit\/cloudxrsession\/configure(config:)","kind":"symbol","type":"topic","fragments":[{"kind":"keyword","text":"func"},{"kind":"text","text":" "},{"kind":"identifier","text":"configure"},{"kind":"text","text":"("},{"kind":"externalParam","text":"config"},{"kind":"text","text":": "},{"kind":"typeIdentifier","preciseIdentifier":"s:10CloudXRKit6ConfigV","text":"Config"},{"kind":"text","text":")"}],"role":"symbol","title":"configure(config:)","identifier":"doc:\/\/com.nvidia.CloudXRKit\/documentation\/CloudXRKit\/CloudXRSession\/configure(config:)"},"doc://com.nvidia.CloudXRKit/documentation/CloudXRKit/CloudXRSession/pause()":{"fragments":[{"text":"func","kind":"keyword"},{"text":" ","kind":"text"},{"text":"pause","kind":"identifier"},{"text":"()","kind":"text"}],"url":"\/documentation\/cloudxrkit\/cloudxrsession\/pause()","kind":"symbol","abstract":[{"text":"Pauses a session without deleting it; it must be resumed with ","type":"text"},{"isActive":true,"identifier":"doc:\/\/com.nvidia.CloudXRKit\/documentation\/CloudXRKit\/CloudXRSession\/resume()","type":"reference"},{"text":" before the server times out.","type":"text"}],"identifier":"doc:\/\/com.nvidia.CloudXRKit\/documentation\/CloudXRKit\/CloudXRSession\/pause()","title":"pause()","type":"topic","role":"symbol"},"doc://com.nvidia.CloudXRKit/documentation/CloudXRKit/CloudXRSession/disconnect()":{"type":"topic","url":"\/documentation\/cloudxrkit\/cloudxrsession\/disconnect()","abstract":[{"type":"text","text":"Disconnects from and ends the session."}],"identifier":"doc:\/\/com.nvidia.CloudXRKit\/documentation\/CloudXRKit\/CloudXRSession\/disconnect()","title":"disconnect()","kind":"symbol","role":"symbol","fragments":[{"text":"func","kind":"keyword"},{"text":" ","kind":"text"},{"text":"disconnect","kind":"identifier"},{"text":"()","kind":"text"}]},"doc://com.nvidia.CloudXRKit/documentation/CloudXRKit/SessionState/disconnected(error:)":{"abstract":[],"identifier":"doc:\/\/com.nvidia.CloudXRKit\/documentation\/CloudXRKit\/SessionState\/disconnected(error:)","fragments":[{"kind":"keyword","text":"case"},{"kind":"text","text":" "},{"kind":"identifier","text":"disconnected"},{"kind":"text","text":"("},{"kind":"externalParam","text":"error"},{"kind":"text","text":": "},{"kind":"typeIdentifier","preciseIdentifier":"s:s6ResultO","text":"Result"},{"kind":"text","text":"<"},{"kind":"typeIdentifier","preciseIdentifier":"s:s4Voida","text":"Void"},{"kind":"text","text":", "},{"kind":"typeIdentifier","preciseIdentifier":"s:10CloudXRKit14StreamingErrorO","text":"StreamingError"},{"kind":"text","text":">)"}],"url":"\/documentation\/cloudxrkit\/sessionstate\/disconnected(error:)","title":"SessionState.disconnected(error:)","role":"symbol","kind":"symbol","type":"topic"},"SessionAPIDiagram.png":{"alt":"Session API diagram","identifier":"SessionAPIDiagram.png","variants":[{"url":"\/images\/com.nvidia.CloudXRKit\/SessionAPIDiagram@2x.png","traits":["2x","light"]},{"url":"\/images\/com.nvidia.CloudXRKit\/SessionAPIDiagram~dark@2x.png","traits":["2x","dark"]}],"type":"image"},"doc://com.nvidia.CloudXRKit/documentation/CloudXRKit/Session/state":{"abstract":[{"type":"text","text":"Client session state."}],"type":"topic","fragments":[{"kind":"keyword","text":"var"},{"kind":"text","text":" "},{"kind":"identifier","text":"state"},{"kind":"text","text":": "},{"preciseIdentifier":"s:10CloudXRKit12SessionStateO","kind":"typeIdentifier","text":"SessionState"}],"identifier":"doc:\/\/com.nvidia.CloudXRKit\/documentation\/CloudXRKit\/Session\/state","url":"\/documentation\/cloudxrkit\/session\/state","title":"state","kind":"symbol","role":"symbol"},"doc://com.nvidia.CloudXRKit/documentation/CloudXRKit/SessionState":{"fragments":[{"text":"enum","kind":"keyword"},{"text":" ","kind":"text"},{"text":"SessionState","kind":"identifier"}],"navigatorTitle":[{"text":"SessionState","kind":"identifier"}],"url":"\/documentation\/cloudxrkit\/sessionstate","abstract":[],"identifier":"doc:\/\/com.nvidia.CloudXRKit\/documentation\/CloudXRKit\/SessionState","type":"topic","title":"SessionState","kind":"symbol","role":"symbol"},"doc://com.nvidia.CloudXRKit/documentation/CloudXRKit/CloudXRSession/resume()":{"url":"\/documentation\/cloudxrkit\/cloudxrsession\/resume()","title":"resume()","identifier":"doc:\/\/com.nvidia.CloudXRKit\/documentation\/CloudXRKit\/CloudXRSession\/resume()","abstract":[{"type":"text","text":"Resumes a previously paused session unless it has timed out on the server. If it has timed out, the session will go to the"},{"type":"text","text":" "},{"identifier":"doc:\/\/com.nvidia.CloudXRKit\/documentation\/CloudXRKit\/SessionState\/disconnected(error:)","isActive":true,"type":"reference"},{"type":"text","text":" state until "},{"identifier":"doc:\/\/com.nvidia.CloudXRKit\/documentation\/CloudXRKit\/CloudXRSession\/connect()","isActive":true,"type":"reference"},{"type":"text","text":" is called again."}],"type":"topic","kind":"symbol","role":"symbol","fragments":[{"text":"func","kind":"keyword"},{"text":" ","kind":"text"},{"text":"resume","kind":"identifier"},{"text":"() ","kind":"text"},{"text":"throws","kind":"keyword"}]}},"variantOverrides":[{"patch":[{"path":"\/identifier\/interfaceLanguage","op":"replace","value":"occ"},{"path":"\/topicSections","op":"add","value":null},{"path":"\/seeAlsoSections","op":"add","value":null}],"traits":[{"interfaceLanguage":"occ"}]}]}